{
  "type": "object",
  "properties": {
    "viewissueslink": {
      "type": "action",
      "selector": "a[href]",
      "control": "action.link",
      "selectContains": "View Issues"
    },
    "isMyViewScreen": {
      "type": "identifier",
      "control": "exists",
      "selectContains": "Assigned to Me (Unresolved)",
      "selector": ".subtle"
    },
    "reportissuelink": {
      "type": "action",
      "selector": "a´href*='bug_report_page']",
      "control": "action.link"
    }
  },
  "connect": [
    {
      "match": [
        "isMyViewScreen"
      ],
      "action": "viewissueslink"
    }
  ]
}
